gesture_wheels/__init__.py
gesture_wheels/core.py
gesture_wheels/wheels.py
gesture_wheels-0.10.0.dist-info/METADATA
gesture_wheels-0.10.0.dist-info/WHEEL
gesture_wheels-0.10.0.dist-info/top_level.txt
gesture_wheels-0.10.0.dist-info/RECORD
