Metadata-Version: 2.4
Name: gesture-wheels
Version: 0.10.0
Summary: Control ESP32 wheeled robots with hand gestures (via Serial)
Home-page: https://pypi.org/project/gesture-wheels/
Author: Your Name
Classifier: Programming Language :: Python :: 3
Classifier: License :: OSI Approved :: MIT License
Classifier: Operating System :: OS Independent
Classifier: Intended Audience :: Education
Classifier: Topic :: Education
Classifier: Topic :: Scientific/Engineering :: Artificial Intelligence
Classifier: Topic :: Software Development :: Embedded Systems
Requires-Python: >=3.7
Requires-Dist: opencv-python
Requires-Dist: mediapipe
Requires-Dist: pyserial
Dynamic: author
Dynamic: classifier
Dynamic: description
Dynamic: description-content-type
Dynamic: home-page
Dynamic: requires-dist
Dynamic: requires-python
Dynamic: summary
